cafe/__init__.py
cafe/fakeData.py
cafe/farm.py
cafelytics-0.1.post3.dist-info/LICENSE.txt
cafelytics-0.1.post3.dist-info/METADATA
cafelytics-0.1.post3.dist-info/WHEEL
cafelytics-0.1.post3.dist-info/top_level.txt
cafelytics-0.1.post3.dist-info/RECORD
