Metadata-Version: 2.1
Name: cafelytics
Version: 0.1.post3
Summary: Open-Source Agricultural Simulation for coffee cooperatives
Home-page: https://github.com/mathematicalmichael/cafelytics.git
Author: Mathematical Michael
Author-email: consistentbayes@gmail.com
License: "MIT"
Project-URL: Documentation, https://cafelytics.rtfd.io/
Platform: any
Classifier: Development Status :: 4 - Beta
Classifier: Programming Language :: Python
Requires-Python: >=3.6
Requires-Dist: numpy
Requires-Dist: matplotlib
Requires-Dist: pandas
Requires-Dist: timedelta
Requires-Dist: dataclasses ; python_version < "3.7"
Requires-Dist: importlib-metadata ; python_version < "3.8"
Provides-Extra: dev
Requires-Dist: faker ; extra == 'dev'
Requires-Dist: pytest ; extra == 'dev'
Requires-Dist: pytest-cov ; extra == 'dev'
Requires-Dist: pre-commit ; extra == 'dev'
Requires-Dist: coveralls ; extra == 'dev'
Requires-Dist: black ; extra == 'dev'
Requires-Dist: flake8 ; extra == 'dev'
